LICENSE
pawl/__init__.py
pawl/constants.py
pawl/core/__init__.py
pawl/core/auth.py
pawl/core/constants.py
pawl/core/exceptions.py
pawl/core/rate_limit.py
pawl/core/requestor.py
pawl/core/session.py
pawl/core/util.py
pawl/endpoints.py
pawl/exceptions.py
pawl/linkedin.py
pawl/service/__init__.py
pawl/service/auth.py
pawl/service/base.py
pawl/service/me.py
pawl/service/reactions.py
pawl/service/util.py
pawl/utils/get_access_token.py
pawl/utils/token_manager.py
pawl-0.1.1.dist-info/LICENSE
pawl-0.1.1.dist-info/WHEEL
pawl-0.1.1.dist-info/METADATA
pawl-0.1.1.dist-info/RECORD
