Metadata-Version: 2.1
Name: pawl
Version: 0.1.1
Summary: PAWL (an acronym for `Python API Wrapper - LinkedIn`) allows for simple access to LinkedIn's API.
License: MIT
Keywords: linkedin,api,wrapper
Author: Kyle J. Burda
Author-email: kylejbdev@gmail.com
Requires-Python: >=3.9,<4.0
Classifier: Intended Audience :: Developers
Classifier: License :: OSI Approved :: MIT License
Classifier: Natural Language :: English
Classifier: Operating System :: OS Independent
Classifier: Programming Language :: Python
Classifier: Programming Language :: Python :: 3
Classifier: Programming Language :: Python :: 3.9
Classifier: Topic :: Utilities
Requires-Dist: requests (>=2.25.1,<3.0.0)
Project-URL: Bug Tracker, https://github.com/kylejb/pawl/issues
Project-URL: Source Code, https://github.com/kylejb/pawl
